{"type":"PR","pr":{"number":5,"head":"c47f81fc74d83f7f1f166164d70d139a6a28b4ed"},"user":"kaleab","status":"draft","branch":"cms/blog/2020-02-01-sample","collection":"blog","commitMessage":"Create Blog “2020-02-01-sample”","title":"Sample","description":"No Description!","objects":{"entry":{"path":"src/pages/blog/2020-02-01-sample.md","sha":"67cf2276dac8742d4c9eebe6efeb3ff1ab1c0e9a"},"files":[{"path":"static/assets/media/theme-15.jpg","sha":"5f9d35f2652f3bbf7925e14d1ac54e86018050ea"}]},"timeStamp":"2020-02-01T05:16:40.895Z","version":"1"}